{
  "name": "market_analyst_ratings",
  "category": "comprehensive",
  "description": "?좊꼸由ъ뒪???ъ옄?섍껄, 紐⑺몴二쇨?, ?깃툒 ?곹븯???대젰 ?섏쭛",
  "version": "1.0",
  "author": "Antigravity",
  "input_schema": {
    "type": "object",
    "properties": {
      "symbol": {
        "type": "string",
        "description": "二쇱떇 ?곗빱 ?щ낵 (?? AAPL)"
      }
    },
    "required": [
      "symbol"
    ]
  },
  "output_schema": {
    "type": "object",
    "properties": {
      "symbol": {
        "type": "string"
      },
      "consensus": {
        "type": "object"
      },
      "recent_recommendations": {
        "type": "array"
      },
      "recent_upgrades_downgrades": {
        "type": "array"
      }
    }
  }
}

